patcher1337/__init__.py
patcher1337-1.0.0.dist-info/LICENSE
patcher1337-1.0.0.dist-info/METADATA
patcher1337-1.0.0.dist-info/WHEEL
patcher1337-1.0.0.dist-info/top_level.txt
patcher1337-1.0.0.dist-info/RECORD
